printree/__init__.py
printree/_ptree.py
tests/__init__.py
tests/test_printree.py
printree-0.2.1.dist-info/LICENSE
printree-0.2.1.dist-info/METADATA
printree-0.2.1.dist-info/WHEEL
printree-0.2.1.dist-info/top_level.txt
printree-0.2.1.dist-info/RECORD
