Metadata-Version: 2.1
Name: printree
Version: 0.2.1
Summary: Pretty print python objects in a tree format.
Home-page: https://github.com/chrizzFTD/printree
Author: Christian López Barrón
Author-email: chris.gfz@gmail.com
Keywords: pprint pformat ptree pretty print tree format formatting
Classifier: Programming Language :: Python :: 3.8
Classifier: Programming Language :: Python :: 3.9
Classifier: Programming Language :: Python :: 3.10
Classifier: Programming Language :: Python :: 3.11
Classifier: Programming Language :: Python :: 3.12
Classifier: Programming Language :: Python :: 3.13
License-File: LICENSE
Provides-Extra: docs
Requires-Dist: sphinx; extra == "docs"
Requires-Dist: sphinx_autodoc_typehints; extra == "docs"
Requires-Dist: sphinx_rtd_theme; extra == "docs"
Requires-Dist: myst-parser; extra == "docs"
